{"is_source_file": false, "format": "", "description": "", "external_files": [], "external_methods": [], "published": [], "classes": [], "methods": [], "calls": [], "search-terms": [], "state": 2, "file_id": 3, "knowledge_revision": 19, "git_revision": "61207e065bf24543b927c342abd4df3ad0865a6f", "hash": "0cf97a81150d3b8904f285780896980d", "format-version": 4, "code-base-name": "website_frontend", "filename": "website_frontend/tsconfig.json", "revision_history": [{"19": "61207e065bf24543b927c342abd4df3ad0865a6f"}]}